pycompss_cli/__init__.py
pycompss_cli/assets/__init__.py
pycompss_cli/assets/enqueue_compss_args.txt
pycompss_cli/assets/runcompss_args.txt
pycompss_cli/cli/__init__.py
pycompss_cli/cli/compss.py
pycompss_cli/cli/dislib.py
pycompss_cli/cli/pycompss.py
pycompss_cli/core/__init__.py
pycompss_cli/core/actions.py
pycompss_cli/core/actions_dispatcher.py
pycompss_cli/core/arguments.py
pycompss_cli/core/cmd_helpers.py
pycompss_cli/core/utils.py
pycompss_cli/core/docker/__init__.py
pycompss_cli/core/docker/actions.py
pycompss_cli/core/docker/arguments.py
pycompss_cli/core/docker/cmd.py
pycompss_cli/core/local/__init__.py
pycompss_cli/core/local/actions.py
pycompss_cli/core/local/arguments.py
pycompss_cli/core/local/cmd.py
pycompss_cli/core/remote/__init__.py
pycompss_cli/core/remote/actions.py
pycompss_cli/core/remote/arguments.py
pycompss_cli/core/remote/cmd.py
pycompss_cli/core/remote/interactive_sc/__init__.py
pycompss_cli/core/remote/interactive_sc/core.py
pycompss_cli/core/remote/interactive_sc/defaults.py
pycompss_cli/core/remote/job_scripts/__init__.py
pycompss_cli/core/remote/job_scripts/cancel.py
pycompss_cli/core/remote/job_scripts/commons.py
pycompss_cli/core/remote/job_scripts/find.py
pycompss_cli/core/remote/job_scripts/info.py
pycompss_cli/core/remote/job_scripts/status.py
pycompss_cli/core/unicore/__init__.py
pycompss_cli/core/unicore/actions.py
pycompss_cli/core/unicore/arguments.py
pycompss_cli/models/__init__.py
pycompss_cli/models/app.py
pycompss_cli-3.3.8.dist-info/LICENSE.txt
pycompss_cli-3.3.8.dist-info/METADATA
pycompss_cli-3.3.8.dist-info/WHEEL
pycompss_cli-3.3.8.dist-info/entry_points.txt
pycompss_cli-3.3.8.dist-info/top_level.txt
pycompss_cli-3.3.8.dist-info/RECORD
