Metadata-Version: 2.1
Name: pycompss-cli
Version: 3.3.8
Summary: PyCOMPSs cli
Home-page: https://compss.bsc.es
Author: Workflows and Distributed Computing Group (WDC) - Barcelona Supercomputing Center (BSC)
Author-email: support-compss@bsc.es
License: Apache 2.0
Classifier: Development Status :: 5 - Production/Stable
Classifier: Environment :: Console
Classifier: Intended Audience :: Developers
Classifier: Intended Audience :: Science/Research
Classifier: License :: OSI Approved :: Apache Software License
Classifier: Operating System :: POSIX :: Linux
Classifier: Operating System :: Unix
Classifier: Operating System :: MacOS
Classifier: Programming Language :: Python :: 3 :: Only
Classifier: Topic :: Software Development
Classifier: Topic :: Scientific/Engineering
Classifier: Topic :: System :: Distributed Computing
Classifier: Topic :: Utilities
License-File: LICENSE.txt
Requires-Dist: setuptools
Requires-Dist: rocrate
